{
  "ignorePatterns": [
    {
      "pattern": "^http://localhost"
    },
    {
      "pattern": "^http://127.0.0.1"
    },
    {
      "pattern": "^https://localhost"
    },
    {
      "pattern": "^https://127.0.0.1"
    },
    {
      "pattern": "^http://kayad"
    },
    {
      "pattern": "^https://kayad"
    },
    {
      "pattern": "^http://api.kayad"
    },
    {
      "pattern": "^https://api.kayad"
    }
  ],
  "timeout": "20s",
  "retryOn429": true,
  "retryCount": 2,
  "aliveStatusCodes": [200, 206, 301, 302, 303, 307, 308]
}
